torchphysics/__init__.py
torchphysics/solver.py
torchphysics/models/FNO.py
torchphysics/models/__init__.py
torchphysics/models/activation_fn.py
torchphysics/models/deepritz.py
torchphysics/models/fcn.py
torchphysics/models/model.py
torchphysics/models/parameter.py
torchphysics/models/qres.py
torchphysics/models/deeponet/branchnets.py
torchphysics/models/deeponet/deeponet.py
torchphysics/models/deeponet/layers.py
torchphysics/models/deeponet/trunknets.py
torchphysics/problem/__init__.py
torchphysics/problem/conditions/__init__.py
torchphysics/problem/conditions/condition.py
torchphysics/problem/conditions/deeponet_condition.py
torchphysics/problem/conditions/variational_condition.py
torchphysics/problem/domains/__init__.py
torchphysics/problem/domains/domain.py
torchphysics/problem/domains/domain0D/__init__.py
torchphysics/problem/domains/domain0D/point.py
torchphysics/problem/domains/domain1D/__init__.py
torchphysics/problem/domains/domain1D/interval.py
torchphysics/problem/domains/domain2D/__init__.py
torchphysics/problem/domains/domain2D/circle.py
torchphysics/problem/domains/domain2D/parallelogram.py
torchphysics/problem/domains/domain2D/shapely_polygon.py
torchphysics/problem/domains/domain2D/triangle.py
torchphysics/problem/domains/domain3D/__init__.py
torchphysics/problem/domains/domain3D/sphere.py
torchphysics/problem/domains/domain3D/trimesh_polyhedron.py
torchphysics/problem/domains/domainoperations/cut.py
torchphysics/problem/domains/domainoperations/intersection.py
torchphysics/problem/domains/domainoperations/product.py
torchphysics/problem/domains/domainoperations/rotate.py
torchphysics/problem/domains/domainoperations/sampler_helper.py
torchphysics/problem/domains/domainoperations/translate.py
torchphysics/problem/domains/domainoperations/union.py
torchphysics/problem/domains/functionsets/FE_functionset.py
torchphysics/problem/domains/functionsets/__init__.py
torchphysics/problem/domains/functionsets/functionset.py
torchphysics-1.0.4.dist-info/AUTHORS.rst
torchphysics-1.0.4.dist-info/LICENSE.txt
torchphysics-1.0.4.dist-info/METADATA
torchphysics-1.0.4.dist-info/NOTICE
torchphysics-1.0.4.dist-info/WHEEL
torchphysics-1.0.4.dist-info/top_level.txt
torchphysics-1.0.4.dist-info/RECORD
