Metadata-Version: 2.1
Name: torchphysics
Version: 1.0.4
Summary: PyTorch implementation of Deep Learning methods to solve differential equations
Home-page: https://github.com/boschresearch/torchphysics
Author: Nick Heilenkötter, Tom Freudenberg
Author-email: nick7@uni-bremen.de, tomfre@uni-bremen.de
License: Apache-2.0
Project-URL: Documentation, https://boschresearch.github.io/torchphysics/index.html
Project-URL: Source, https://github.com/boschresearch/torchphysics
Project-URL: Changelog, https://github.com/boschresearch/torchphysics/blob/main/CHANGELOG.rst
Platform: any
Classifier: Development Status :: 5 - Production/Stable
Classifier: Programming Language :: Python
License-File: LICENSE.txt
License-File: NOTICE
License-File: AUTHORS.rst
Requires-Dist: torch>=2.0.0
Requires-Dist: pytorch-lightning>=2.0.0
Requires-Dist: numpy<2.0,>=1.20.2
Requires-Dist: matplotlib>=3.0.0
Requires-Dist: scipy>=1.6.3
Requires-Dist: importlib-metadata
Requires-Dist: jupyter
Provides-Extra: all
Requires-Dist: networkx>=2.5.1; extra == "all"
Requires-Dist: trimesh>=3.9.19; extra == "all"
Requires-Dist: shapely>=1.7.1; extra == "all"
Requires-Dist: rtree>=0.9.7; extra == "all"
Provides-Extra: testing
Requires-Dist: setuptools; extra == "testing"
Requires-Dist: pytest; extra == "testing"
Requires-Dist: pytest-cov; extra == "testing"
